{"mapCode":"BB","shareInfos":[{"content":"<?xml version=\"1.0\" encoding=\"UTF-8\" ?>\r\n<MapRetCfg>\r\n<MapRet>\r\n<Point xpos=\"625263\" ypos=\"503316\"/>\r\n<Point xpos=\"630672\" ypos=\"503316\"/>\r\n<Point xpos=\"630672\" ypos=\"501658\"/>\r\n<Point xpos=\"625263\" ypos=\"501658\"/>\r\n<Area color_a=\"255\" color_r=\"218\" color_g=\"220\" color_b=\"223\"/>\r\n</MapRet>\r\n<MapRet>\r\n<Point xpos=\"636081\" ypos=\"503158\"/>\r\n<Point xpos=\"641925\" ypos=\"503158\"/>\r\n<Point xpos=\"641925\" ypos=\"501697\"/>\r\n<Point xpos=\"636081\" ypos=\"501697\"/>\r\n<Area color_a=\"255\" color_r=\"218\" color_g=\"220\" color_b=\"223\"/>\r\n</MapRet>\r\n<MapRet>\r\n<Point xpos=\"646307\" ypos=\"503040\"/>\r\n<Point xpos=\"651440\" ypos=\"503040\"/>\r\n<Point xpos=\"651440\" ypos=\"501737\"/>\r\n<Point xpos=\"646307\" ypos=\"501737\"/>\r\n<Area color_a=\"255\" color_r=\"218\" color_g=\"220\" color_b=\"223\"/>\r\n</MapRet>\r\n<MapRet>\r\n<Point xpos=\"615589\" ypos=\"503079\"/>\r\n<Point xpos=\"620722\" ypos=\"503079\"/>\r\n<Point xpos=\"620722\" ypos=\"501579\"/>\r\n<Point xpos=\"615589\" ypos=\"501579\"/>\r\n<Area color_a=\"255\" color_r=\"218\" color_g=\"220\" color_b=\"223\"/>\r\n</MapRet>\r\n<MapRet>\r\n<Point xpos=\"651638\" ypos=\"503276\"/>\r\n<Point xpos=\"654638\" ypos=\"503276\"/>\r\n<Point xpos=\"654638\" ypos=\"501697\"/>\r\n<Point xpos=\"651638\" ypos=\"501697\"/>\r\n<Area color_a=\"255\" color_r=\"218\" color_g=\"220\" color_b=\"223\"/>\r\n</MapRet>\r\n<MapRet>\r\n<Point xpos=\"609385\" ypos=\"509332\"/>\r\n<Point xpos=\"612881\" ypos=\"509332\"/>\r\n<Point xpos=\"612881\" ypos=\"508080\"/>\r\n<Point xpos=\"609385\" ypos=\"508080\"/>\r\n<Area color_a=\"255\" color_r=\"218\" color_g=\"220\" color_b=\"223\"/>\r\n</MapRet>\r\n<MapRet>\r\n<Point xpos=\"615385\" ypos=\"509379\"/>\r\n<Point xpos=\"619543\" ypos=\"509379\"/>\r\n<Point xpos=\"619543\" ypos=\"508103\"/>\r\n<Point xpos=\"615385\" ypos=\"508103\"/>\r\n<Area color_a=\"255\" color_r=\"218\" color_g=\"220\" color_b=\"223\"/>\r\n</MapRet>\r\n<MapRet>\r\n<Point xpos=\"627740\" ypos=\"509119\"/>\r\n<Point xpos=\"631685\" ypos=\"509119\"/>\r\n<Point xpos=\"631685\" ypos=\"508103\"/>\r\n<Point xpos=\"627740\" ypos=\"508103\"/>\r\n<Area color_a=\"255\" color_r=\"218\" color_g=\"220\" color_b=\"223\"/>\r\n</MapRet>\r\n<MapRet>\r\n<Point xpos=\"621173\" ypos=\"509308\"/>\r\n<Point xpos=\"625591\" ypos=\"509308\"/>\r\n<Point xpos=\"625591\" ypos=\"508056\"/>\r\n<Point xpos=\"621173\" ypos=\"508056\"/>\r\n<Area color_a=\"255\" color_r=\"218\" color_g=\"220\" color_b=\"223\"/>\r\n</MapRet>\r\n<MapRet>\r\n<Point xpos=\"613263\" ypos=\"376269\"/>\r\n<Point xpos=\"613356\" ypos=\"376269\"/>\r\n<Point xpos=\"613356\" ypos=\"378131\"/>\r\n<Point xpos=\"613263\" ypos=\"378131\"/>\r\n<Area color_a=\"255\" color_r=\"218\" color_g=\"220\" color_b=\"223\"/>\r\n</MapRet>\r\n<MapRet>\r\n<Point xpos=\"621947\" ypos=\"372507\"/>\r\n<Point xpos=\"627656\" ypos=\"372507\"/>\r\n<Point xpos=\"627656\" ypos=\"360106\"/>\r\n<Point xpos=\"621947\" ypos=\"360106\"/>\r\n<Area color_a=\"255\" color_r=\"218\" color_g=\"220\" color_b=\"223\"/>\r\n</MapRet>\r\n<MapRet>\r\n<Point xpos=\"610066\" ypos=\"498317\"/>\r\n<Point xpos=\"619397\" ypos=\"498317\"/>\r\n<Point xpos=\"619397\" ypos=\"497080\"/>\r\n<Point xpos=\"610066\" ypos=\"497080\"/>\r\n<Area color_a=\"255\" color_r=\"218\" color_g=\"220\" color_b=\"223\"/>\r\n</MapRet>\r\n<MapRet>\r\n<Point xpos=\"603440\" ypos=\"480701\"/>\r\n<Point xpos=\"606538\" ypos=\"480701\"/>\r\n<Point xpos=\"606538\" ypos=\"470620\"/>\r\n<Point xpos=\"603440\" ypos=\"470620\"/>\r\n<Area color_a=\"255\" color_r=\"218\" color_g=\"220\" color_b=\"223\"/>\r\n</MapRet>\r\n<MapRet>\r\n<Point xpos=\"604019\" ypos=\"439296\"/>\r\n<Point xpos=\"605988\" ypos=\"439296\"/>\r\n<Point xpos=\"605988\" ypos=\"434200\"/>\r\n<Point xpos=\"604019\" ypos=\"434200\"/>\r\n<Area color_a=\"255\" color_r=\"218\" color_g=\"220\" color_b=\"223\"/>\r\n</MapRet>\r\n<MapRet>\r\n<Point xpos=\"609635\" ypos=\"480949\"/>\r\n<Point xpos=\"614286\" ypos=\"480949\"/>\r\n<Point xpos=\"614286\" ypos=\"493999\"/>\r\n<Point xpos=\"609635\" ypos=\"493999\"/>\r\n<Area color_a=\"255\" color_r=\"218\" color_g=\"220\" color_b=\"223\"/>\r\n</MapRet>\r\n<MapRet>\r\n<Point xpos=\"615186\" ypos=\"493848\"/>\r\n<Point xpos=\"619335\" ypos=\"493848\"/>\r\n<Point xpos=\"619335\" ypos=\"480949\"/>\r\n<Point xpos=\"615186\" ypos=\"480949\"/>\r\n<Area color_a=\"255\" color_r=\"218\" color_g=\"220\" color_b=\"223\"/>\r\n</MapRet>\r\n<MapRet>\r\n<Point xpos=\"609536\" ypos=\"473549\"/>\r\n<Point xpos=\"613736\" ypos=\"473549\"/>\r\n<Point xpos=\"613736\" ypos=\"444498\"/>\r\n<Point xpos=\"609536\" ypos=\"444498\"/>\r\n<Area color_a=\"255\" color_r=\"218\" color_g=\"220\" color_b=\"223\"/>\r\n</MapRet>\r\n<MapRet>\r\n<Point xpos=\"615585\" ypos=\"473148\"/>\r\n<Point xpos=\"615635\" ypos=\"473148\"/>\r\n<Point xpos=\"615635\" ypos=\"471598\"/>\r\n<Point xpos=\"615585\" ypos=\"471598\"/>\r\n<Area color_a=\"255\" color_r=\"218\" color_g=\"220\" color_b=\"223\"/>\r\n</MapRet>\r\n<MapRet>\r\n<Point xpos=\"609477\" ypos=\"438865\"/>\r\n<Point xpos=\"613477\" ypos=\"438865\"/>\r\n<Point xpos=\"613477\" ypos=\"429949\"/>\r\n<Point xpos=\"609477\" ypos=\"429949\"/>\r\n<Area color_a=\"255\" color_r=\"218\" color_g=\"220\" color_b=\"223\"/>\r\n</MapRet>\r\n<MapRet>\r\n<Point xpos=\"615144\" ypos=\"438199\"/>\r\n<Point xpos=\"618227\" ypos=\"438199\"/>\r\n<Point xpos=\"618227\" ypos=\"430199\"/>\r\n<Point xpos=\"615144\" ypos=\"430199\"/>\r\n<Area color_a=\"255\" color_r=\"218\" color_g=\"220\" color_b=\"223\"/>\r\n</MapRet>\r\n<MapRet>\r\n<Point xpos=\"614727\" ypos=\"430115\"/>\r\n<Point xpos=\"618977\" ypos=\"430115\"/>\r\n<Point xpos=\"618977\" ypos=\"438699\"/>\r\n<Point xpos=\"614727\" ypos=\"438699\"/>\r\n<Area color_a=\"255\" color_r=\"218\" color_g=\"220\" color_b=\"223\"/>\r\n</MapRet>\r\n<MapRet>\r\n<Point xpos=\"609311\" ypos=\"426449\"/>\r\n<Point xpos=\"613394\" ypos=\"426449\"/>\r\n<Point xpos=\"613394\" ypos=\"401865\"/>\r\n<Point xpos=\"609311\" ypos=\"401865\"/>\r\n<Area color_a=\"255\" color_r=\"218\" color_g=\"220\" color_b=\"223\"/>\r\n</MapRet>\r\n<MapRet>\r\n<Point xpos=\"614894\" ypos=\"426282\"/>\r\n<Point xpos=\"620227\" ypos=\"426282\"/>\r\n<Point xpos=\"620227\" ypos=\"401865\"/>\r\n<Point xpos=\"614894\" ypos=\"401865\"/>\r\n<Area color_a=\"255\" color_r=\"218\" color_g=\"220\" color_b=\"223\"/>\r\n</MapRet>\r\n<MapRet>\r\n<Point xpos=\"608780\" ypos=\"395013\"/>\r\n<Point xpos=\"613422\" ypos=\"395013\"/>\r\n<Point xpos=\"613422\" ypos=\"385156\"/>\r\n<Point xpos=\"608780\" ypos=\"385156\"/>\r\n<Area color_a=\"255\" color_r=\"218\" color_g=\"220\" color_b=\"223\"/>\r\n</MapRet>\r\n<MapRet>\r\n<Point xpos=\"614708\" ypos=\"394727\"/>\r\n<Point xpos=\"619208\" ypos=\"394727\"/>\r\n<Point xpos=\"619208\" ypos=\"385298\"/>\r\n<Point xpos=\"614708\" ypos=\"385298\"/>\r\n<Area color_a=\"255\" color_r=\"218\" color_g=\"220\" color_b=\"223\"/>\r\n</MapRet>\r\n<MapRet>\r\n<Point xpos=\"610422\" ypos=\"379941\"/>\r\n<Point xpos=\"613780\" ypos=\"379941\"/>\r\n<Point xpos=\"613780\" ypos=\"365941\"/>\r\n<Point xpos=\"610422\" ypos=\"365941\"/>\r\n<Area color_a=\"255\" color_r=\"218\" color_g=\"220\" color_b=\"223\"/>\r\n</MapRet>\r\n<MapRet>\r\n<Point xpos=\"614137\" ypos=\"379941\"/>\r\n<Point xpos=\"617565\" ypos=\"379941\"/>\r\n<Point xpos=\"617565\" ypos=\"365798\"/>\r\n<Point xpos=\"614137\" ypos=\"365798\"/>\r\n<Area color_a=\"255\" color_r=\"218\" color_g=\"220\" color_b=\"223\"/>\r\n</MapRet>\r\n<MapRet>\r\n<Point xpos=\"630878\" ypos=\"402619\"/>\r\n<Point xpos=\"629528\" ypos=\"402619\"/>\r\n<Point xpos=\"629528\" ypos=\"402439\"/>\r\n<Point xpos=\"630878\" ypos=\"402439\"/>\r\n<Area color_a=\"255\" color_r=\"218\" color_g=\"220\" color_b=\"223\"/>\r\n</MapRet>\r\n<MapRet>\r\n<Point xpos=\"603041\" ypos=\"420580\"/>\r\n<Point xpos=\"604916\" ypos=\"420580\"/>\r\n<Point xpos=\"604916\" ypos=\"412034\"/>\r\n<Point xpos=\"603041\" ypos=\"412034\"/>\r\n<Area color_a=\"255\" color_r=\"218\" color_g=\"220\" color_b=\"223\"/>\r\n</MapRet>\r\n<MapRet>\r\n<Point xpos=\"603790\" ypos=\"464281\"/>\r\n<Point xpos=\"606555\" ypos=\"464281\"/>\r\n<Point xpos=\"606555\" ypos=\"456613\"/>\r\n<Point xpos=\"603790\" ypos=\"456613\"/>\r\n<Area color_a=\"255\" color_r=\"218\" color_g=\"220\" color_b=\"223\"/>\r\n</MapRet>\r\n<MapRet>\r\n<Point xpos=\"604238\" ypos=\"432723\"/>\r\n<Point xpos=\"606597\" ypos=\"432723\"/>\r\n<Point xpos=\"606597\" ypos=\"425814\"/>\r\n<Point xpos=\"604238\" ypos=\"425814\"/>\r\n<Area color_a=\"255\" color_r=\"218\" color_g=\"220\" color_b=\"223\"/>\r\n</MapRet>\r\n<MapRet>\r\n<Point xpos=\"602272\" ypos=\"411435\"/>\r\n<Point xpos=\"606204\" ypos=\"411435\"/>\r\n<Point xpos=\"606204\" ypos=\"401212\"/>\r\n<Point xpos=\"602272\" ypos=\"401212\"/>\r\n<Area color_a=\"255\" color_r=\"218\" color_g=\"220\" color_b=\"223\"/>\r\n</MapRet>\r\n<MapRet>\r\n<Point xpos=\"602609\" ypos=\"400763\"/>\r\n<Point xpos=\"606429\" ypos=\"400763\"/>\r\n<Point xpos=\"606429\" ypos=\"394416\"/>\r\n<Point xpos=\"602609\" ypos=\"394416\"/>\r\n<Area color_a=\"255\" color_r=\"218\" color_g=\"220\" color_b=\"223\"/>\r\n</MapRet>\r\n<MapRet>\r\n<Point xpos=\"627653\" ypos=\"473347\"/>\r\n<Point xpos=\"631129\" ypos=\"473347\"/>\r\n<Point xpos=\"631129\" ypos=\"460183\"/>\r\n<Point xpos=\"627653\" ypos=\"460183\"/>\r\n<Area color_a=\"255\" color_r=\"218\" color_g=\"220\" color_b=\"223\"/>\r\n</MapRet>\r\n<MapRet>\r\n<Point xpos=\"622211\" ypos=\"475902\"/>\r\n<Point xpos=\"625950\" ypos=\"475902\"/>\r\n<Point xpos=\"625950\" ypos=\"460180\"/>\r\n<Point xpos=\"622211\" ypos=\"460180\"/>\r\n<Area color_a=\"255\" color_r=\"218\" color_g=\"220\" color_b=\"223\"/>\r\n</MapRet>\r\n<MapRet>\r\n<Point xpos=\"627598\" ypos=\"444616\"/>\r\n<Point xpos=\"630698\" ypos=\"444616\"/>\r\n<Point xpos=\"630698\" ypos=\"455333\"/>\r\n<Point xpos=\"627598\" ypos=\"455333\"/>\r\n<Area color_a=\"255\" color_r=\"218\" color_g=\"220\" color_b=\"223\"/>\r\n</MapRet>\r\n<MapRet>\r\n<Point xpos=\"621857\" ypos=\"459961\"/>\r\n<Point xpos=\"623796\" ypos=\"459961\"/>\r\n<Point xpos=\"623796\" ypos=\"459279\"/>\r\n<Point xpos=\"621857\" ypos=\"459279\"/>\r\n<Area color_a=\"255\" color_r=\"218\" color_g=\"220\" color_b=\"223\"/>\r\n</MapRet>\r\n<MapRet>\r\n<Point xpos=\"619624\" ypos=\"440442\"/>\r\n<Point xpos=\"624688\" ypos=\"440442\"/>\r\n<Point xpos=\"624688\" ypos=\"439238\"/>\r\n<Point xpos=\"619624\" ypos=\"439238\"/>\r\n<Area color_a=\"255\" color_r=\"218\" color_g=\"220\" color_b=\"223\"/>\r\n</MapRet>\r\n<MapRet>\r\n<Point xpos=\"622282\" ypos=\"481344\"/>\r\n<Point xpos=\"625852\" ypos=\"481344\"/>\r\n<Point xpos=\"625852\" ypos=\"494036\"/>\r\n<Point xpos=\"622282\" ypos=\"494036\"/>\r\n<Area color_a=\"255\" color_r=\"218\" color_g=\"220\" color_b=\"223\"/>\r\n</MapRet>\r\n<MapRet>\r\n<Point xpos=\"628100\" ypos=\"481299\"/>\r\n<Point xpos=\"631273\" ypos=\"481299\"/>\r\n<Point xpos=\"631273\" ypos=\"494036\"/>\r\n<Point xpos=\"628100\" ypos=\"494036\"/>\r\n<Area color_a=\"255\" color_r=\"218\" color_g=\"220\" color_b=\"223\"/>\r\n</MapRet>\r\n<MapRet>\r\n<Point xpos=\"629029\" ypos=\"440333\"/>\r\n<Point xpos=\"633979\" ypos=\"440333\"/>\r\n<Point xpos=\"633979\" ypos=\"439297\"/>\r\n<Point xpos=\"629029\" ypos=\"439297\"/>\r\n<Area color_a=\"255\" color_r=\"218\" color_g=\"220\" color_b=\"223\"/>\r\n</MapRet>\r\n<MapRet>\r\n<Point xpos=\"699518\" ypos=\"353950\"/>\r\n<Point xpos=\"704861\" ypos=\"353950\"/>\r\n<Point xpos=\"704861\" ypos=\"346513\"/>\r\n<Point xpos=\"699518\" ypos=\"346513\"/>\r\n<Area color_a=\"255\" color_r=\"218\" color_g=\"220\" color_b=\"223\"/>\r\n</MapRet>\r\n<MapRet>\r\n<Point xpos=\"693518\" ypos=\"353825\"/>\r\n<Point xpos=\"697393\" ypos=\"353825\"/>\r\n<Point xpos=\"697393\" ypos=\"353231\"/>\r\n<Point xpos=\"693518\" ypos=\"353231\"/>\r\n<Area color_a=\"255\" color_r=\"218\" color_g=\"220\" color_b=\"223\"/>\r\n</MapRet>\r\n<MapRet>\r\n<Point xpos=\"693518\" ypos=\"353825\"/>\r\n<Point xpos=\"699174\" ypos=\"353825\"/>\r\n<Point xpos=\"699174\" ypos=\"346481\"/>\r\n<Point xpos=\"693518\" ypos=\"346481\"/>\r\n<Area color_a=\"255\" color_r=\"218\" color_g=\"220\" color_b=\"223\"/>\r\n</MapRet>\r\n<MapRet>\r\n<Point xpos=\"648360\" ypos=\"464468\"/>\r\n<Point xpos=\"652305\" ypos=\"464468\"/>\r\n<Point xpos=\"652305\" ypos=\"481992\"/>\r\n<Point xpos=\"648360\" ypos=\"481992\"/>\r\n<Area color_a=\"255\" color_r=\"218\" color_g=\"220\" color_b=\"223\"/>\r\n</MapRet>\r\n<MapRet>\r\n<Point xpos=\"657880\" ypos=\"464439\"/>\r\n<Point xpos=\"654421\" ypos=\"464439\"/>\r\n<Point xpos=\"654421\" ypos=\"481878\"/>\r\n<Point xpos=\"657880\" ypos=\"481878\"/>\r\n<Area color_a=\"255\" color_r=\"218\" color_g=\"220\" color_b=\"223\"/>\r\n</MapRet>\r\n<MapRet>\r\n<Point xpos=\"649498\" ypos=\"460641\"/>\r\n<Point xpos=\"653280\" ypos=\"460641\"/>\r\n<Point xpos=\"653280\" ypos=\"444324\"/>\r\n<Point xpos=\"649498\" ypos=\"444324\"/>\r\n<Area color_a=\"255\" color_r=\"218\" color_g=\"220\" color_b=\"223\"/>\r\n</MapRet>\r\n<MapRet>\r\n<Point xpos=\"654793\" ypos=\"444540\"/>\r\n<Point xpos=\"658251\" ypos=\"444540\"/>\r\n<Point xpos=\"658251\" ypos=\"460569\"/>\r\n<Point xpos=\"654793\" ypos=\"460569\"/>\r\n<Area color_a=\"255\" color_r=\"218\" color_g=\"220\" color_b=\"223\"/>\r\n</MapRet>\r\n<MapRet>\r\n<Point xpos=\"649679\" ypos=\"438957\"/>\r\n<Point xpos=\"654125\" ypos=\"438957\"/>\r\n<Point xpos=\"654125\" ypos=\"421824\"/>\r\n<Point xpos=\"649679\" ypos=\"421824\"/>\r\n<Area color_a=\"255\" color_r=\"218\" color_g=\"220\" color_b=\"223\"/>\r\n</MapRet>\r\n<MapRet>\r\n<Point xpos=\"655237\" ypos=\"438804\"/>\r\n<Point xpos=\"659606\" ypos=\"438804\"/>\r\n<Point xpos=\"659606\" ypos=\"422169\"/>\r\n<Point xpos=\"655237\" ypos=\"422169\"/>\r\n<Area color_a=\"255\" color_r=\"218\" color_g=\"220\" color_b=\"223\"/>\r\n</MapRet>\r\n<MapRet>\r\n<Point xpos=\"603512\" ypos=\"371387\"/>\r\n<Point xpos=\"605522\" ypos=\"371387\"/>\r\n<Point xpos=\"605522\" ypos=\"361815\"/>\r\n<Point xpos=\"603512\" ypos=\"361815\"/>\r\n<Area color_a=\"255\" color_r=\"218\" color_g=\"220\" color_b=\"223\"/>\r\n</MapRet>\r\n<MapRet>\r\n<Point xpos=\"614783\" ypos=\"444406\"/>\r\n<Point xpos=\"619310\" ypos=\"444406\"/>\r\n<Point xpos=\"619310\" ypos=\"473832\"/>\r\n<Point xpos=\"614783\" ypos=\"473832\"/>\r\n<Area color_a=\"255\" color_r=\"218\" color_g=\"220\" color_b=\"223\"/>\r\n</MapRet>\r\n<MapRet>\r\n<Point xpos=\"625978\" ypos=\"444655\"/>\r\n<Point xpos=\"623186\" ypos=\"444655\"/>\r\n<Point xpos=\"623186\" ypos=\"455310\"/>\r\n<Point xpos=\"625978\" ypos=\"455310\"/>\r\n<Area color_a=\"255\" color_r=\"218\" color_g=\"220\" color_b=\"223\"/>\r\n</MapRet>\r\n<MapRet>\r\n<Point xpos=\"645973\" ypos=\"451670\"/>\r\n<Point xpos=\"647589\" ypos=\"451670\"/>\r\n<Point xpos=\"647589\" ypos=\"446548\"/>\r\n<Point xpos=\"645973\" ypos=\"446548\"/>\r\n<Area color_a=\"255\" color_r=\"218\" color_g=\"220\" color_b=\"223\"/>\r\n</MapRet>\r\n<MapRet>\r\n<Point xpos=\"627915\" ypos=\"372437\"/>\r\n<Point xpos=\"632549\" ypos=\"372437\"/>\r\n<Point xpos=\"632549\" ypos=\"360082\"/>\r\n<Point xpos=\"627915\" ypos=\"360082\"/>\r\n<Area color_a=\"255\" color_r=\"218\" color_g=\"220\" color_b=\"223\"/>\r\n</MapRet>\r\n<MapRet>\r\n<Point xpos=\"600328\" ypos=\"393986\"/>\r\n<Point xpos=\"604103\" ypos=\"393986\"/>\r\n<Point xpos=\"604103\" ypos=\"390996\"/>\r\n<Point xpos=\"600328\" ypos=\"390996\"/>\r\n<Area color_a=\"255\" color_r=\"218\" color_g=\"220\" color_b=\"223\"/>\r\n</MapRet>\r\n<MapRet>\r\n<Point xpos=\"620529\" ypos=\"498259\"/>\r\n<Point xpos=\"625365\" ypos=\"498259\"/>\r\n<Point xpos=\"625365\" ypos=\"496945\"/>\r\n<Point xpos=\"620529\" ypos=\"496945\"/>\r\n<Area color_a=\"255\" color_r=\"218\" color_g=\"220\" color_b=\"223\"/>\r\n</MapRet>\r\n<MapRet>\r\n<Point xpos=\"626244\" ypos=\"498263\"/>\r\n<Point xpos=\"635773\" ypos=\"498263\"/>\r\n<Point xpos=\"635773\" ypos=\"496872\"/>\r\n<Point xpos=\"626244\" ypos=\"496872\"/>\r\n<Area color_a=\"255\" color_r=\"218\" color_g=\"220\" color_b=\"223\"/>\r\n</MapRet>\r\n<MapRet>\r\n<Point xpos=\"642485\" ypos=\"440417\"/>\r\n<Point xpos=\"647260\" ypos=\"440417\"/>\r\n<Point xpos=\"647260\" ypos=\"439235\"/>\r\n<Point xpos=\"642485\" ypos=\"439235\"/>\r\n<Area color_a=\"255\" color_r=\"218\" color_g=\"220\" color_b=\"223\"/>\r\n</MapRet>\r\n<MapRet>\r\n<Point xpos=\"655369\" ypos=\"417818\"/>\r\n<Point xpos=\"660289\" ypos=\"417818\"/>\r\n<Point xpos=\"660289\" ypos=\"411406\"/>\r\n<Point xpos=\"655369\" ypos=\"411406\"/>\r\n<Area color_a=\"255\" color_r=\"218\" color_g=\"220\" color_b=\"223\"/>\r\n</MapRet>\r\n<MapRet>\r\n<Point xpos=\"647472\" ypos=\"418674\"/>\r\n<Point xpos=\"648665\" ypos=\"418674\"/>\r\n<Point xpos=\"648665\" ypos=\"413183\"/>\r\n<Point xpos=\"647472\" ypos=\"413183\"/>\r\n<Area color_a=\"255\" color_r=\"218\" color_g=\"220\" color_b=\"223\"/>\r\n</MapRet>\r\n<MapRet>\r\n<Point xpos=\"647301\" ypos=\"428461\"/>\r\n<Point xpos=\"648734\" ypos=\"428461\"/>\r\n<Point xpos=\"648734\" ypos=\"422595\"/>\r\n<Point xpos=\"647301\" ypos=\"422595\"/>\r\n<Area color_a=\"255\" color_r=\"218\" color_g=\"220\" color_b=\"223\"/>\r\n</MapRet>\r\n<MapRet>\r\n<Point xpos=\"649666\" ypos=\"417810\"/>\r\n<Point xpos=\"654351\" ypos=\"417810\"/>\r\n<Point xpos=\"654351\" ypos=\"411304\"/>\r\n<Point xpos=\"649666\" ypos=\"411304\"/>\r\n<Area color_a=\"255\" color_r=\"218\" color_g=\"220\" color_b=\"223\"/>\r\n</MapRet>\r\n<MapRet>\r\n<Point xpos=\"647379\" ypos=\"399331\"/>\r\n<Point xpos=\"648806\" ypos=\"399331\"/>\r\n<Point xpos=\"648806\" ypos=\"392974\"/>\r\n<Point xpos=\"647379\" ypos=\"392974\"/>\r\n<Area color_a=\"255\" color_r=\"218\" color_g=\"220\" color_b=\"223\"/>\r\n</MapRet>\r\n<MapRet>\r\n<Point xpos=\"647515\" ypos=\"392019\"/>\r\n<Point xpos=\"649009\" ypos=\"392019\"/>\r\n<Point xpos=\"649009\" ypos=\"379207\"/>\r\n<Point xpos=\"647515\" ypos=\"379207\"/>\r\n<Area color_a=\"255\" color_r=\"218\" color_g=\"220\" color_b=\"223\"/>\r\n</MapRet>\r\n<MapRet>\r\n<Point xpos=\"634833\" ypos=\"372366\"/>\r\n<Point xpos=\"638471\" ypos=\"372366\"/>\r\n<Point xpos=\"638471\" ypos=\"368760\"/>\r\n<Point xpos=\"634833\" ypos=\"368760\"/>\r\n<Area color_a=\"255\" color_r=\"218\" color_g=\"220\" color_b=\"223\"/>\r\n</MapRet>\r\n<MapRet>\r\n<Point xpos=\"634899\" ypos=\"367834\"/>\r\n<Point xpos=\"639265\" ypos=\"367834\"/>\r\n<Point xpos=\"639265\" ypos=\"359896\"/>\r\n<Point xpos=\"634899\" ypos=\"359896\"/>\r\n<Area color_a=\"255\" color_r=\"218\" color_g=\"220\" color_b=\"223\"/>\r\n</MapRet>\r\n<MapRet>\r\n<Point xpos=\"641812\" ypos=\"367702\"/>\r\n<Point xpos=\"646244\" ypos=\"367702\"/>\r\n<Point xpos=\"646244\" ypos=\"359664\"/>\r\n<Point xpos=\"641812\" ypos=\"359664\"/>\r\n<Area color_a=\"255\" color_r=\"218\" color_g=\"220\" color_b=\"223\"/>\r\n</MapRet>\r\n<MapRet>\r\n<Point xpos=\"618472\" ypos=\"355267\"/>\r\n<Point xpos=\"631230\" ypos=\"355267\"/>\r\n<Point xpos=\"631230\" ypos=\"353501\"/>\r\n<Point xpos=\"618472\" ypos=\"353501\"/>\r\n<Area color_a=\"255\" color_r=\"218\" color_g=\"220\" color_b=\"223\"/>\r\n</MapRet>\r\n<MapRet>\r\n<Point xpos=\"633622\" ypos=\"355096\"/>\r\n<Point xpos=\"645240\" ypos=\"355096\"/>\r\n<Point xpos=\"645240\" ypos=\"353302\"/>\r\n<Point xpos=\"633622\" ypos=\"353302\"/>\r\n<Area color_a=\"255\" color_r=\"218\" color_g=\"220\" color_b=\"223\"/>\r\n</MapRet>\r\n<MapRet>\r\n<Point xpos=\"650073\" ypos=\"359625\"/>\r\n<Point xpos=\"653243\" ypos=\"359625\"/>\r\n<Point xpos=\"653243\" ypos=\"372509\"/>\r\n<Point xpos=\"650073\" ypos=\"372509\"/>\r\n<Area color_a=\"255\" color_r=\"218\" color_g=\"220\" color_b=\"223\"/>\r\n</MapRet>\r\n<MapRet>\r\n<Point xpos=\"654857\" ypos=\"359625\"/>\r\n<Point xpos=\"658201\" ypos=\"359625\"/>\r\n<Point xpos=\"658201\" ypos=\"372509\"/>\r\n<Point xpos=\"654857\" ypos=\"372509\"/>\r\n<Area color_a=\"255\" color_r=\"218\" color_g=\"220\" color_b=\"223\"/>\r\n</MapRet>\r\n<MapRet>\r\n<Point xpos=\"645464\" ypos=\"355024\"/>\r\n<Point xpos=\"650617\" ypos=\"355024\"/>\r\n<Point xpos=\"650617\" ypos=\"353185\"/>\r\n<Point xpos=\"645464\" ypos=\"353185\"/>\r\n<Area color_a=\"255\" color_r=\"218\" color_g=\"220\" color_b=\"223\"/>\r\n</MapRet>\r\n<MapRet>\r\n<Point xpos=\"641476\" ypos=\"438140\"/>\r\n<Point xpos=\"646045\" ypos=\"438140\"/>\r\n<Point xpos=\"646045\" ypos=\"430998\"/>\r\n<Point xpos=\"641476\" ypos=\"430998\"/>\r\n<Area color_a=\"255\" color_r=\"218\" color_g=\"220\" color_b=\"223\"/>\r\n</MapRet>\r\n<MapRet>\r\n<Point xpos=\"641336\" ypos=\"430169\"/>\r\n<Point xpos=\"646083\" ypos=\"430169\"/>\r\n<Point xpos=\"646083\" ypos=\"425450\"/>\r\n<Point xpos=\"641336\" ypos=\"425450\"/>\r\n<Area color_a=\"255\" color_r=\"218\" color_g=\"220\" color_b=\"223\"/>\r\n</MapRet>\r\n<MapRet>\r\n<Point xpos=\"639179\" ypos=\"395032\"/>\r\n<Point xpos=\"634866\" ypos=\"395032\"/>\r\n<Point xpos=\"634866\" ypos=\"422606\"/>\r\n<Point xpos=\"639179\" ypos=\"422606\"/>\r\n<Area color_a=\"255\" color_r=\"218\" color_g=\"220\" color_b=\"223\"/>\r\n</MapRet>\r\n<MapRet>\r\n<Point xpos=\"641214\" ypos=\"422509\"/>\r\n<Point xpos=\"645867\" ypos=\"422509\"/>\r\n<Point xpos=\"645867\" ypos=\"394790\"/>\r\n<Point xpos=\"641214\" ypos=\"394790\"/>\r\n<Area color_a=\"255\" color_r=\"218\" color_g=\"220\" color_b=\"223\"/>\r\n</MapRet>\r\n<MapRet>\r\n<Point xpos=\"638827\" ypos=\"424125\"/>\r\n<Point xpos=\"634932\" ypos=\"424125\"/>\r\n<Point xpos=\"634932\" ypos=\"437921\"/>\r\n<Point xpos=\"638827\" ypos=\"437921\"/>\r\n<Area color_a=\"255\" color_r=\"218\" color_g=\"220\" color_b=\"223\"/>\r\n</MapRet>\r\n<MapRet>\r\n<Point xpos=\"641103\" ypos=\"392113\"/>\r\n<Point xpos=\"645975\" ypos=\"392113\"/>\r\n<Point xpos=\"645975\" ypos=\"378676\"/>\r\n<Point xpos=\"641103\" ypos=\"378676\"/>\r\n<Area color_a=\"255\" color_r=\"218\" color_g=\"220\" color_b=\"223\"/>\r\n</MapRet>\r\n<MapRet>\r\n<Point xpos=\"635329\" ypos=\"392113\"/>\r\n<Point xpos=\"639352\" ypos=\"392113\"/>\r\n<Point xpos=\"639352\" ypos=\"378566\"/>\r\n<Point xpos=\"635329\" ypos=\"378566\"/>\r\n<Area color_a=\"255\" color_r=\"218\" color_g=\"220\" color_b=\"223\"/>\r\n</MapRet>\r\n<MapRet>\r\n<Point xpos=\"628462\" ypos=\"390791\"/>\r\n<Point xpos=\"632724\" ypos=\"390791\"/>\r\n<Point xpos=\"632724\" ypos=\"378931\"/>\r\n<Point xpos=\"628462\" ypos=\"378931\"/>\r\n<Area color_a=\"255\" color_r=\"218\" color_g=\"220\" color_b=\"223\"/>\r\n</MapRet>\r\n<MapRet>\r\n<Point xpos=\"626414\" ypos=\"379162\"/>\r\n<Point xpos=\"622053\" ypos=\"379162\"/>\r\n<Point xpos=\"622053\" ypos=\"390725\"/>\r\n<Point xpos=\"626414\" ypos=\"390725\"/>\r\n<Area color_a=\"255\" color_r=\"218\" color_g=\"220\" color_b=\"223\"/>\r\n</MapRet>\r\n<MapRet>\r\n<Point xpos=\"628561\" ypos=\"436083\"/>\r\n<Point xpos=\"632922\" ypos=\"436083\"/>\r\n<Point xpos=\"632922\" ypos=\"393335\"/>\r\n<Point xpos=\"628561\" ypos=\"393335\"/>\r\n<Area color_a=\"255\" color_r=\"218\" color_g=\"220\" color_b=\"223\"/>\r\n</MapRet>\r\n<MapRet>\r\n<Point xpos=\"625654\" ypos=\"435819\"/>\r\n<Point xpos=\"621690\" ypos=\"435819\"/>\r\n<Point xpos=\"621690\" ypos=\"393202\"/>\r\n<Point xpos=\"625654\" ypos=\"393202\"/>\r\n<Area color_a=\"255\" color_r=\"218\" color_g=\"220\" color_b=\"223\"/>\r\n</MapRet>\r\n<MapRet>\r\n<Point xpos=\"644693\" ypos=\"443655\"/>\r\n<Point xpos=\"641143\" ypos=\"443655\"/>\r\n<Point xpos=\"641143\" ypos=\"455630\"/>\r\n<Point xpos=\"644693\" ypos=\"455630\"/>\r\n<Area color_a=\"255\" color_r=\"218\" color_g=\"220\" color_b=\"223\"/>\r\n</MapRet>\r\n<MapRet>\r\n<Point xpos=\"633248\" ypos=\"456423\"/>\r\n<Point xpos=\"637327\" ypos=\"456423\"/>\r\n<Point xpos=\"637327\" ypos=\"443655\"/>\r\n<Point xpos=\"633248\" ypos=\"443655\"/>\r\n<Area color_a=\"255\" color_r=\"218\" color_g=\"220\" color_b=\"223\"/>\r\n</MapRet>\r\n<MapRet>\r\n<Point xpos=\"639893\" ypos=\"462841\"/>\r\n<Point xpos=\"642734\" ypos=\"462841\"/>\r\n<Point xpos=\"642734\" ypos=\"460098\"/>\r\n<Point xpos=\"639893\" ypos=\"460098\"/>\r\n<Area color_a=\"255\" color_r=\"218\" color_g=\"220\" color_b=\"223\"/>\r\n</MapRet>\r\n<MapRet>\r\n<Point xpos=\"639795\" ypos=\"477473\"/>\r\n<Point xpos=\"642865\" ypos=\"477473\"/>\r\n<Point xpos=\"642865\" ypos=\"468720\"/>\r\n<Point xpos=\"639795\" ypos=\"468720\"/>\r\n<Area color_a=\"255\" color_r=\"218\" color_g=\"220\" color_b=\"223\"/>\r\n</MapRet>\r\n<MapRet>\r\n<Point xpos=\"639990\" ypos=\"467746\"/>\r\n<Point xpos=\"642738\" ypos=\"467746\"/>\r\n<Point xpos=\"642738\" ypos=\"465053\"/>\r\n<Point xpos=\"639990\" ypos=\"465053\"/>\r\n<Area color_a=\"255\" color_r=\"218\" color_g=\"220\" color_b=\"223\"/>\r\n</MapRet>\r\n<MapRet>\r\n<Point xpos=\"632922\" ypos=\"484474\"/>\r\n<Point xpos=\"636677\" ypos=\"484474\"/>\r\n<Point xpos=\"636677\" ypos=\"481074\"/>\r\n<Point xpos=\"632922\" ypos=\"481074\"/>\r\n<Area color_a=\"255\" color_r=\"218\" color_g=\"220\" color_b=\"223\"/>\r\n</MapRet>\r\n<MapRet>\r\n<Point xpos=\"632863\" ypos=\"488169\"/>\r\n<Point xpos=\"636647\" ypos=\"488169\"/>\r\n<Point xpos=\"636647\" ypos=\"485450\"/>\r\n<Point xpos=\"632863\" ypos=\"485450\"/>\r\n<Area color_a=\"255\" color_r=\"218\" color_g=\"220\" color_b=\"223\"/>\r\n</MapRet>\r\n<MapRet>\r\n<Point xpos=\"638707\" ypos=\"484227\"/>\r\n<Point xpos=\"642269\" ypos=\"484227\"/>\r\n<Point xpos=\"642269\" ypos=\"480591\"/>\r\n<Point xpos=\"638707\" ypos=\"480591\"/>\r\n<Area color_a=\"255\" color_r=\"218\" color_g=\"220\" color_b=\"223\"/>\r\n</MapRet>\r\n<MapRet>\r\n<Point xpos=\"638340\" ypos=\"493959\"/>\r\n<Point xpos=\"642783\" ypos=\"493959\"/>\r\n<Point xpos=\"642783\" ypos=\"488193\"/>\r\n<Point xpos=\"638340\" ypos=\"488193\"/>\r\n<Area color_a=\"255\" color_r=\"218\" color_g=\"220\" color_b=\"223\"/>\r\n</MapRet>\r\n<MapRet>\r\n<Point xpos=\"644612\" ypos=\"464878\"/>\r\n<Point xpos=\"646349\" ypos=\"464878\"/>\r\n<Point xpos=\"646349\" ypos=\"476362\"/>\r\n<Point xpos=\"644612\" ypos=\"476362\"/>\r\n<Area color_a=\"255\" color_r=\"218\" color_g=\"220\" color_b=\"223\"/>\r\n</MapRet>\r\n<MapRet>\r\n<Point xpos=\"633103\" ypos=\"476909\"/>\r\n<Point xpos=\"638104\" ypos=\"476909\"/>\r\n<Point xpos=\"638104\" ypos=\"459718\"/>\r\n<Point xpos=\"633103\" ypos=\"459718\"/>\r\n<Area color_a=\"255\" color_r=\"218\" color_g=\"220\" color_b=\"223\"/>\r\n</MapRet>\r\n<MapRet>\r\n<Point xpos=\"607952\" ypos=\"412840\"/>\r\n<Point xpos=\"609513\" ypos=\"412840\"/>\r\n<Point xpos=\"609513\" ypos=\"403118\"/>\r\n<Point xpos=\"607952\" ypos=\"403118\"/>\r\n<Area color_a=\"255\" color_r=\"218\" color_g=\"220\" color_b=\"223\"/>\r\n</MapRet>\r\n<MapRet>\r\n<Point xpos=\"607988\" ypos=\"423978\"/>\r\n<Point xpos=\"609728\" ypos=\"423978\"/>\r\n<Point xpos=\"609728\" ypos=\"414140\"/>\r\n<Point xpos=\"607988\" ypos=\"414140\"/>\r\n<Area color_a=\"255\" color_r=\"218\" color_g=\"220\" color_b=\"223\"/>\r\n</MapRet>\r\n<MapRet>\r\n<Point xpos=\"636478\" ypos=\"498139\"/>\r\n<Point xpos=\"647012\" ypos=\"498139\"/>\r\n<Point xpos=\"647012\" ypos=\"496772\"/>\r\n<Point xpos=\"636478\" ypos=\"496772\"/>\r\n<Area color_a=\"255\" color_r=\"218\" color_g=\"220\" color_b=\"223\"/>\r\n</MapRet>\r\n<MapRet>\r\n<Point xpos=\"609149\" ypos=\"501692\"/>\r\n<Point xpos=\"655360\" ypos=\"501692\"/>\r\n<Point xpos=\"655360\" ypos=\"498263\"/>\r\n<Point xpos=\"609149\" ypos=\"498263\"/>\r\n<Area color_a=\"255\" color_r=\"218\" color_g=\"220\" color_b=\"223\"/>\r\n</MapRet>\r\n<MapRet>\r\n<Point xpos=\"647241\" ypos=\"498177\"/>\r\n<Point xpos=\"655490\" ypos=\"498177\"/>\r\n<Point xpos=\"655490\" ypos=\"496652\"/>\r\n<Point xpos=\"647241\" ypos=\"496652\"/>\r\n<Area color_a=\"255\" color_r=\"218\" color_g=\"220\" color_b=\"223\"/>\r\n</MapRet>\r\n<MapRet>\r\n<Point xpos=\"607822\" ypos=\"362790\"/>\r\n<Point xpos=\"614382\" ypos=\"362790\"/>\r\n<Point xpos=\"614382\" ypos=\"361064\"/>\r\n<Point xpos=\"607822\" ypos=\"361064\"/>\r\n<Area color_a=\"255\" color_r=\"218\" color_g=\"220\" color_b=\"223\"/>\r\n</MapRet>\r\n<MapRet>\r\n<Point xpos=\"647394\" ypos=\"410362\"/>\r\n<Point xpos=\"648956\" ypos=\"410362\"/>\r\n<Point xpos=\"648956\" ypos=\"400945\"/>\r\n<Point xpos=\"647394\" ypos=\"400945\"/>\r\n<Area color_a=\"255\" color_r=\"218\" color_g=\"220\" color_b=\"223\"/>\r\n</MapRet>\r\n<MapRet>\r\n<Point xpos=\"642634\" ypos=\"508945\"/>\r\n<Point xpos=\"652865\" ypos=\"508945\"/>\r\n<Point xpos=\"652865\" ypos=\"507763\"/>\r\n<Point xpos=\"642634\" ypos=\"507763\"/>\r\n<Area color_a=\"255\" color_r=\"218\" color_g=\"220\" color_b=\"223\"/>\r\n</MapRet>\r\n<MapRet>\r\n<Point xpos=\"642310\" ypos=\"508974\"/>\r\n<Point xpos=\"632523\" ypos=\"508974\"/>\r\n<Point xpos=\"632523\" ypos=\"507776\"/>\r\n<Point xpos=\"642310\" ypos=\"507776\"/>\r\n<Area color_a=\"255\" color_r=\"218\" color_g=\"220\" color_b=\"223\"/>\r\n</MapRet>\r\n<MapRet>\r\n<Point xpos=\"678265\" ypos=\"508922\"/>\r\n<Point xpos=\"684866\" ypos=\"508922\"/>\r\n<Point xpos=\"684866\" ypos=\"507462\"/>\r\n<Point xpos=\"678265\" ypos=\"507462\"/>\r\n<Area color_a=\"255\" color_r=\"218\" color_g=\"220\" color_b=\"223\"/>\r\n</MapRet>\r\n<MapRet>\r\n<Point xpos=\"674891\" ypos=\"508829\"/>\r\n<Point xpos=\"668642\" ypos=\"508829\"/>\r\n<Point xpos=\"668642\" ypos=\"507294\"/>\r\n<Point xpos=\"674891\" ypos=\"507294\"/>\r\n<Area color_a=\"255\" color_r=\"218\" color_g=\"220\" color_b=\"223\"/>\r\n</MapRet>\r\n<MapRet>\r\n<Point xpos=\"653741\" ypos=\"501572\"/>\r\n<Point xpos=\"655696\" ypos=\"501572\"/>\r\n<Point xpos=\"655696\" ypos=\"499368\"/>\r\n<Point xpos=\"653741\" ypos=\"499368\"/>\r\n<Area color_a=\"255\" color_r=\"218\" color_g=\"220\" color_b=\"223\"/>\r\n</MapRet>\r\n<RetName start_x=\"615708\" start_y=\"501381\" end_x=\"649190\" end_y=\"498459\" size=\"46.751873\" font=\"Microsoft YaHei\" font_color_a=\"255\" font_color_r=\"0\" font_color_g=\"0\" font_color_b=\"0\">M    F     S    T    K    A    0   0</RetName>\r\n<RetName start_x=\"651952\" start_y=\"502882\" end_x=\"654558\" end_y=\"501917\" size=\"15.439957\" font=\"Microsoft YaHei\" font_color_a=\"255\" font_color_r=\"0\" font_color_g=\"0\" font_color_b=\"0\">???</RetName>\r\n<RetName start_x=\"609621\" start_y=\"509073\" end_x=\"613165\" end_y=\"508301\" size=\"12.352056\" font=\"Microsoft YaHei\" font_color_a=\"255\" font_color_r=\"0\" font_color_g=\"0\" font_color_b=\"0\">MFLFTB00</RetName>\r\n<RetName start_x=\"615858\" start_y=\"509094\" end_x=\"619212\" end_y=\"508312\" size=\"12.512202\" font=\"Microsoft YaHei\" font_color_a=\"255\" font_color_r=\"0\" font_color_g=\"0\" font_color_b=\"0\">MFLFTC00</RetName>\r\n<RetName start_x=\"621717\" start_y=\"509119\" end_x=\"625048\" end_y=\"508328\" size=\"12.655740\" font=\"Microsoft YaHei\" font_color_a=\"255\" font_color_r=\"0\" font_color_g=\"0\" font_color_b=\"0\">MFLFTD00</RetName>\r\n<RetName start_x=\"628236\" start_y=\"509001\" end_x=\"631378\" end_y=\"508250\" size=\"12.016122\" font=\"Microsoft YaHei\" font_color_a=\"255\" font_color_r=\"0\" font_color_g=\"0\" font_color_b=\"0\">MFLFTE00</RetName>\r\n<RetName start_x=\"608946\" start_y=\"391130\" end_x=\"613462\" end_y=\"389602\" size=\"24.448000\" font=\"Arial\" font_color_a=\"255\" font_color_r=\"0\" font_color_g=\"0\" font_color_b=\"0\">BAP#M</RetName>\r\n<RetName start_x=\"610598\" start_y=\"373753\" end_x=\"613842\" end_y=\"372560\" size=\"19.087786\" font=\"Arial\" font_color_a=\"255\" font_color_r=\"0\" font_color_g=\"0\" font_color_b=\"0\">LLC#M</RetName>\r\n<RetName start_x=\"622280\" start_y=\"368513\" end_x=\"627641\" end_y=\"366558\" size=\"31.280010\" font=\"Arial\" font_color_a=\"255\" font_color_r=\"0\" font_color_g=\"0\" font_color_b=\"0\">LOC M</RetName>\r\n<RetName start_x=\"613318\" start_y=\"498585\" end_x=\"614984\" end_y=\"497363\" size=\"20.000000\" font=\"Arial\" font_color_a=\"255\" font_color_r=\"0\" font_color_g=\"0\" font_color_b=\"0\">403</RetName>\r\n<RetName start_x=\"603760\" start_y=\"479423\" end_x=\"604792\" end_y=\"472120\" size=\"36.000000\" font=\"Microsoft YaHei\" font_color_a=\"255\" font_color_r=\"0\" font_color_g=\"0\" font_color_b=\"0\">4\n2\n7</RetName>\r\n<RetName start_x=\"604019\" start_y=\"439383\" end_x=\"604830\" end_y=\"434171\" size=\"30.000000\" font=\"Arial\" font_color_a=\"255\" font_color_r=\"0\" font_color_g=\"0\" font_color_b=\"0\">4\n2\n5</RetName>\r\n<RetName start_x=\"614835\" start_y=\"391206\" end_x=\"619316\" end_y=\"389642\" size=\"25.023914\" font=\"Arial\" font_color_a=\"255\" font_color_r=\"0\" font_color_g=\"0\" font_color_b=\"0\">BAP#N</RetName>\r\n<RetName start_x=\"614439\" start_y=\"373682\" end_x=\"617635\" end_y=\"372585\" size=\"17.552389\" font=\"Arial\" font_color_a=\"255\" font_color_r=\"0\" font_color_g=\"0\" font_color_b=\"0\">LLC#N</RetName>\r\n<RetName start_x=\"620823\" start_y=\"423232\" end_x=\"627879\" end_y=\"421372\" size=\"29.759684\" font=\"Arial\" font_color_a=\"255\" font_color_r=\"0\" font_color_g=\"0\" font_color_b=\"0\">SRG#M</RetName>\r\n<RetName start_x=\"628574\" start_y=\"423099\" end_x=\"636697\" end_y=\"421304\" size=\"28.720205\" font=\"Microsoft YaHei\" font_color_a=\"255\" font_color_r=\"0\" font_color_g=\"0\" font_color_b=\"0\">SRG#N</RetName>\r\n<RetName start_x=\"623636\" start_y=\"387820\" end_x=\"625526\" end_y=\"384219\" size=\"32.000000\" font=\"Arial\" font_color_a=\"255\" font_color_r=\"0\" font_color_g=\"0\" font_color_b=\"0\">2D\nM</RetName>\r\n<RetName start_x=\"629549\" start_y=\"387676\" end_x=\"631439\" end_y=\"384075\" size=\"32.000000\" font=\"Arial\" font_color_a=\"255\" font_color_r=\"0\" font_color_g=\"0\" font_color_b=\"0\">2D\nN</RetName>\r\n<RetName start_x=\"603506\" start_y=\"419155\" end_x=\"605168\" end_y=\"413852\" size=\"26.591869\" font=\"Microsoft YaHei\" font_color_a=\"255\" font_color_r=\"0\" font_color_g=\"0\" font_color_b=\"0\">4 2 3</RetName>\r\n<RetName start_x=\"603904\" start_y=\"464508\" end_x=\"607290\" end_y=\"462460\" size=\"32.768139\" font=\"Microsoft YaHei\" font_color_a=\"255\" font_color_r=\"0\" font_color_g=\"0\" font_color_b=\"0\">4</RetName>\r\n<RetName start_x=\"603806\" start_y=\"462208\" end_x=\"607585\" end_y=\"460077\" size=\"34.096115\" font=\"Microsoft YaHei\" font_color_a=\"255\" font_color_r=\"0\" font_color_g=\"0\" font_color_b=\"0\">2</RetName>\r\n<RetName start_x=\"603805\" start_y=\"459186\" end_x=\"607520\" end_y=\"456922\" size=\"36.224220\" font=\"Microsoft YaHei\" font_color_a=\"255\" font_color_r=\"0\" font_color_g=\"0\" font_color_b=\"0\">6</RetName>\r\n<RetName start_x=\"604238\" start_y=\"432104\" end_x=\"607047\" end_y=\"430293\" size=\"36.224220\" font=\"Microsoft YaHei\" font_color_a=\"255\" font_color_r=\"0\" font_color_g=\"0\" font_color_b=\"0\">4</RetName>\r\n<RetName start_x=\"604183\" start_y=\"430027\" end_x=\"606991\" end_y=\"428216\" size=\"36.224220\" font=\"Microsoft YaHei\" font_color_a=\"255\" font_color_r=\"0\" font_color_g=\"0\" font_color_b=\"0\">2</RetName>\r\n<RetName start_x=\"604041\" start_y=\"427892\" end_x=\"606849\" end_y=\"426081\" size=\"36.224220\" font=\"Microsoft YaHei\" font_color_a=\"255\" font_color_r=\"0\" font_color_g=\"0\" font_color_b=\"0\">4</RetName>\r\n<RetName start_x=\"602775\" start_y=\"410211\" end_x=\"605733\" end_y=\"408400\" size=\"36.224220\" font=\"Microsoft YaHei\" font_color_a=\"255\" font_color_r=\"0\" font_color_g=\"0\" font_color_b=\"0\">4</RetName>\r\n<RetName start_x=\"602893\" start_y=\"400715\" end_x=\"605852\" end_y=\"398904\" size=\"36.224220\" font=\"Microsoft YaHei\" font_color_a=\"255\" font_color_r=\"0\" font_color_g=\"0\" font_color_b=\"0\">4</RetName>\r\n<RetName start_x=\"602746\" start_y=\"407459\" end_x=\"605704\" end_y=\"405648\" size=\"36.224220\" font=\"Microsoft YaHei\" font_color_a=\"255\" font_color_r=\"0\" font_color_g=\"0\" font_color_b=\"0\">2</RetName>\r\n<RetName start_x=\"602982\" start_y=\"398851\" end_x=\"605941\" end_y=\"397039\" size=\"36.224220\" font=\"Microsoft YaHei\" font_color_a=\"255\" font_color_r=\"0\" font_color_g=\"0\" font_color_b=\"0\">2</RetName>\r\n<RetName start_x=\"602685\" start_y=\"404916\" end_x=\"605644\" end_y=\"403105\" size=\"36.224220\" font=\"Microsoft YaHei\" font_color_a=\"255\" font_color_r=\"0\" font_color_g=\"0\" font_color_b=\"0\">2</RetName>\r\n<RetName start_x=\"603069\" start_y=\"396840\" end_x=\"606027\" end_y=\"395029\" size=\"36.224220\" font=\"Microsoft YaHei\" font_color_a=\"255\" font_color_r=\"0\" font_color_g=\"0\" font_color_b=\"0\">1</RetName>\r\n<RetName start_x=\"615970\" start_y=\"502848\" end_x=\"620589\" end_y=\"501769\" size=\"17.264135\" font=\"Microsoft YaHei\" font_color_a=\"255\" font_color_r=\"0\" font_color_g=\"0\" font_color_b=\"0\">AGVPORT4</RetName>\r\n<RetName start_x=\"625765\" start_y=\"502927\" end_x=\"630384\" end_y=\"501865\" size=\"16.992168\" font=\"Microsoft YaHei\" font_color_a=\"255\" font_color_r=\"0\" font_color_g=\"0\" font_color_b=\"0\">AGVPORT3</RetName>\r\n<RetName start_x=\"636477\" start_y=\"502967\" end_x=\"641812\" end_y=\"501720\" size=\"19.952169\" font=\"Microsoft YaHei\" font_color_a=\"255\" font_color_r=\"0\" font_color_g=\"0\" font_color_b=\"0\">AGVPORT2</RetName>\r\n<RetName start_x=\"646950\" start_y=\"502927\" end_x=\"651410\" end_y=\"501849\" size=\"17.248037\" font=\"Microsoft YaHei\" font_color_a=\"255\" font_color_r=\"0\" font_color_g=\"0\" font_color_b=\"0\">AGVPORT1</RetName>\r\n<RetName start_x=\"627655\" start_y=\"450789\" end_x=\"630776\" end_y=\"449730\" size=\"16.943876\" font=\"Microsoft YaHei\" font_color_a=\"255\" font_color_r=\"0\" font_color_g=\"0\" font_color_b=\"0\">AOI#N</RetName>\r\n<RetName start_x=\"620840\" start_y=\"440199\" end_x=\"624678\" end_y=\"439186\" size=\"16.208187\" font=\"Microsoft YaHei\" font_color_a=\"255\" font_color_r=\"0\" font_color_g=\"0\" font_color_b=\"0\">410</RetName>\r\n<RetName start_x=\"627760\" start_y=\"468344\" end_x=\"631357\" end_y=\"467179\" size=\"18.640213\" font=\"Microsoft YaHei\" font_color_a=\"255\" font_color_r=\"0\" font_color_g=\"0\" font_color_b=\"0\">GGA#V</RetName>\r\n<RetName start_x=\"622540\" start_y=\"488752\" end_x=\"625787\" end_y=\"487793\" size=\"15.344301\" font=\"Microsoft YaHei\" font_color_a=\"255\" font_color_r=\"0\" font_color_g=\"0\" font_color_b=\"0\">GDM#M</RetName>\r\n<RetName start_x=\"628092\" start_y=\"488742\" end_x=\"631417\" end_y=\"487687\" size=\"16.879875\" font=\"Microsoft YaHei\" font_color_a=\"255\" font_color_r=\"0\" font_color_g=\"0\" font_color_b=\"0\">GDM#L</RetName>\r\n<RetName start_x=\"622059\" start_y=\"468314\" end_x=\"625825\" end_y=\"467221\" size=\"17.487808\" font=\"Microsoft YaHei\" font_color_a=\"255\" font_color_r=\"0\" font_color_g=\"0\" font_color_b=\"0\">GGA#W</RetName>\r\n<RetName start_x=\"629858\" start_y=\"440472\" end_x=\"633793\" end_y=\"439216\" size=\"20.096106\" font=\"Microsoft YaHei\" font_color_a=\"255\" font_color_r=\"0\" font_color_g=\"0\" font_color_b=\"0\">409</RetName>\r\n<RetName start_x=\"699830\" start_y=\"351325\" end_x=\"704393\" end_y=\"350182\" size=\"18.288572\" font=\"Microsoft YaHei\" font_color_a=\"255\" font_color_r=\"0\" font_color_g=\"0\" font_color_b=\"0\">MFLFTG00</RetName>\r\n<RetName start_x=\"693893\" start_y=\"351356\" end_x=\"698955\" end_y=\"350036\" size=\"21.119627\" font=\"Microsoft YaHei\" font_color_a=\"255\" font_color_r=\"0\" font_color_g=\"0\" font_color_b=\"0\">MFLFTF00</RetName>\r\n<RetName start_x=\"648345\" start_y=\"474159\" end_x=\"652322\" end_y=\"472918\" size=\"19.855999\" font=\"Microsoft YaHei\" font_color_a=\"255\" font_color_r=\"0\" font_color_g=\"0\" font_color_b=\"0\">GOT#M</RetName>\r\n<RetName start_x=\"654473\" start_y=\"474162\" end_x=\"657883\" end_y=\"472970\" size=\"19.071678\" font=\"Microsoft YaHei\" font_color_a=\"255\" font_color_r=\"0\" font_color_g=\"0\" font_color_b=\"0\">GOT#N</RetName>\r\n<RetName start_x=\"649649\" start_y=\"454722\" end_x=\"653399\" end_y=\"453460\" size=\"20.191935\" font=\"Microsoft YaHei\" font_color_a=\"255\" font_color_r=\"0\" font_color_g=\"0\" font_color_b=\"0\">GRF#M</RetName>\r\n<RetName start_x=\"654886\" start_y=\"454614\" end_x=\"658359\" end_y=\"453403\" size=\"19.375954\" font=\"Microsoft YaHei\" font_color_a=\"255\" font_color_r=\"0\" font_color_g=\"0\" font_color_b=\"0\">GRF#N</RetName>\r\n<RetName start_x=\"649700\" start_y=\"433087\" end_x=\"654190\" end_y=\"431677\" size=\"22.560040\" font=\"Microsoft YaHei\" font_color_a=\"255\" font_color_r=\"0\" font_color_g=\"0\" font_color_b=\"0\">MPB#M</RetName>\r\n<RetName start_x=\"655254\" start_y=\"433012\" end_x=\"659717\" end_y=\"431629\" size=\"22.127804\" font=\"Microsoft YaHei\" font_color_a=\"255\" font_color_r=\"0\" font_color_g=\"0\" font_color_b=\"0\">MPB#N</RetName>\r\n<RetName start_x=\"603990\" start_y=\"369410\" end_x=\"606402\" end_y=\"364441\" size=\"37.791943\" font=\"Microsoft YaHei\" font_color_a=\"255\" font_color_r=\"0\" font_color_g=\"0\" font_color_b=\"0\">4 2 0</RetName>\r\n<RetName start_x=\"649611\" start_y=\"368095\" end_x=\"653793\" end_y=\"366623\" size=\"23.552187\" font=\"Microsoft YaHei\" font_color_a=\"255\" font_color_r=\"0\" font_color_g=\"0\" font_color_b=\"0\">KSP#M</RetName>\r\n<RetName start_x=\"655271\" start_y=\"368054\" end_x=\"661357\" end_y=\"366551\" size=\"24.047880\" font=\"Microsoft YaHei\" font_color_a=\"255\" font_color_r=\"0\" font_color_g=\"0\" font_color_b=\"0\">KSP#N</RetName>\r\n<RetName start_x=\"609913\" start_y=\"489221\" end_x=\"614387\" end_y=\"487914\" size=\"20.912096\" font=\"Microsoft YaHei\" font_color_a=\"255\" font_color_r=\"0\" font_color_g=\"0\" font_color_b=\"0\">PAT#M</RetName>\r\n<RetName start_x=\"610070\" start_y=\"487660\" end_x=\"613763\" end_y=\"486614\" size=\"16.735733\" font=\"Microsoft YaHei\" font_color_a=\"255\" font_color_r=\"0\" font_color_g=\"0\" font_color_b=\"0\">?POL?</RetName>\r\n<RetName start_x=\"615375\" start_y=\"489117\" end_x=\"619329\" end_y=\"487764\" size=\"21.647919\" font=\"Microsoft YaHei\" font_color_a=\"255\" font_color_r=\"0\" font_color_g=\"0\" font_color_b=\"0\">PAT#N</RetName>\r\n<RetName start_x=\"615688\" start_y=\"487608\" end_x=\"618861\" end_y=\"486630\" size=\"15.647951\" font=\"Microsoft YaHei\" font_color_a=\"255\" font_color_r=\"0\" font_color_g=\"0\" font_color_b=\"0\">?POL?</RetName>\r\n<RetName start_x=\"609651\" start_y=\"461181\" end_x=\"613674\" end_y=\"459803\" size=\"22.047901\" font=\"Microsoft YaHei\" font_color_a=\"255\" font_color_r=\"0\" font_color_g=\"0\" font_color_b=\"0\">LLO#M</RetName>\r\n<RetName start_x=\"614981\" start_y=\"461205\" end_x=\"619469\" end_y=\"459740\" size=\"23.439892\" font=\"Microsoft YaHei\" font_color_a=\"255\" font_color_r=\"0\" font_color_g=\"0\" font_color_b=\"0\">LLO#N</RetName>\r\n<RetName start_x=\"609705\" start_y=\"436868\" end_x=\"613460\" end_y=\"435663\" size=\"19.280272\" font=\"Microsoft YaHei\" font_color_a=\"255\" font_color_r=\"0\" font_color_g=\"0\" font_color_b=\"0\">CPC#N</RetName>\r\n<RetName start_x=\"615084\" start_y=\"436799\" end_x=\"618872\" end_y=\"435532\" size=\"20.272038\" font=\"Microsoft YaHei\" font_color_a=\"255\" font_color_r=\"0\" font_color_g=\"0\" font_color_b=\"0\">CPC#P</RetName>\r\n<RetName start_x=\"609773\" start_y=\"434872\" end_x=\"613460\" end_y=\"434129\" size=\"11.888224\" font=\"Microsoft YaHei\" font_color_a=\"255\" font_color_r=\"0\" font_color_g=\"0\" font_color_b=\"0\">?Line Cut?</RetName>\r\n<RetName start_x=\"615252\" start_y=\"434907\" end_x=\"618907\" end_y=\"434161\" size=\"11.936061\" font=\"Microsoft YaHei\" font_color_a=\"255\" font_color_r=\"0\" font_color_g=\"0\" font_color_b=\"0\">?Line Cut?</RetName>\r\n<RetName start_x=\"609158\" start_y=\"417140\" end_x=\"613445\" end_y=\"415715\" size=\"22.800167\" font=\"Microsoft YaHei\" font_color_a=\"255\" font_color_r=\"0\" font_color_g=\"0\" font_color_b=\"0\">BOP#M</RetName>\r\n<RetName start_x=\"615484\" start_y=\"417217\" end_x=\"620372\" end_y=\"415796\" size=\"22.736383\" font=\"Microsoft YaHei\" font_color_a=\"255\" font_color_r=\"0\" font_color_g=\"0\" font_color_b=\"0\">BOP#N</RetName>\r\n<RetName start_x=\"614591\" start_y=\"372351\" end_x=\"617629\" end_y=\"371529\" size=\"13.152051\" font=\"Microsoft YaHei\" font_color_a=\"255\" font_color_r=\"0\" font_color_g=\"0\" font_color_b=\"0\">?ODD?</RetName>\r\n<RetName start_x=\"622259\" start_y=\"466892\" end_x=\"625773\" end_y=\"465822\" size=\"17.120184\" font=\"Microsoft YaHei\" font_color_a=\"255\" font_color_r=\"0\" font_color_g=\"0\" font_color_b=\"0\">?GM?</RetName>\r\n<RetName start_x=\"627708\" start_y=\"466942\" end_x=\"631171\" end_y=\"465924\" size=\"16.287659\" font=\"Microsoft YaHei\" font_color_a=\"255\" font_color_r=\"0\" font_color_g=\"0\" font_color_b=\"0\">?GM?</RetName>\r\n<RetName start_x=\"622711\" start_y=\"487657\" end_x=\"625933\" end_y=\"486705\" size=\"15.232427\" font=\"Microsoft YaHei\" font_color_a=\"255\" font_color_r=\"0\" font_color_g=\"0\" font_color_b=\"0\">?DM?</RetName>\r\n<RetName start_x=\"628356\" start_y=\"487731\" end_x=\"631505\" end_y=\"486751\" size=\"15.679784\" font=\"Microsoft YaHei\" font_color_a=\"255\" font_color_r=\"0\" font_color_g=\"0\" font_color_b=\"0\">?DM?</RetName>\r\n<RetName start_x=\"623186\" start_y=\"450720\" end_x=\"626074\" end_y=\"449707\" size=\"16.208134\" font=\"Microsoft YaHei\" font_color_a=\"255\" font_color_r=\"0\" font_color_g=\"0\" font_color_b=\"0\">AOI#M</RetName>\r\n<RetName start_x=\"648884\" start_y=\"472785\" end_x=\"652564\" end_y=\"471864\" size=\"14.735854\" font=\"Microsoft YaHei\" font_color_a=\"255\" font_color_r=\"0\" font_color_g=\"0\" font_color_b=\"0\">?AFT?</RetName>\r\n<RetName start_x=\"654735\" start_y=\"472880\" end_x=\"657943\" end_y=\"472017\" size=\"13.808012\" font=\"Microsoft YaHei\" font_color_a=\"255\" font_color_r=\"0\" font_color_g=\"0\" font_color_b=\"0\">?AFT?</RetName>\r\n<RetName start_x=\"609528\" start_y=\"415615\" end_x=\"612571\" end_y=\"414479\" size=\"18.175581\" font=\"Microsoft YaHei\" font_color_a=\"255\" font_color_r=\"0\" font_color_g=\"0\" font_color_b=\"0\">?BD?</RetName>\r\n<RetName start_x=\"615747\" start_y=\"415794\" end_x=\"619504\" end_y=\"414707\" size=\"17.392178\" font=\"Microsoft YaHei\" font_color_a=\"255\" font_color_r=\"0\" font_color_g=\"0\" font_color_b=\"0\">?BD?</RetName>\r\n<RetName start_x=\"609356\" start_y=\"389666\" end_x=\"612873\" end_y=\"388798\" size=\"13.887733\" font=\"Microsoft YaHei\" font_color_a=\"255\" font_color_r=\"0\" font_color_g=\"0\" font_color_b=\"0\">?AMT?</RetName>\r\n<RetName start_x=\"615561\" start_y=\"389604\" end_x=\"618909\" end_y=\"388723\" size=\"14.096377\" font=\"Microsoft YaHei\" font_color_a=\"255\" font_color_r=\"0\" font_color_g=\"0\" font_color_b=\"0\">?AMT?</RetName>\r\n<RetName start_x=\"649939\" start_y=\"453142\" end_x=\"653263\" end_y=\"452055\" size=\"17.392178\" font=\"Microsoft YaHei\" font_color_a=\"255\" font_color_r=\"0\" font_color_g=\"0\" font_color_b=\"0\">?SCF?</RetName>\r\n<RetName start_x=\"655211\" start_y=\"453143\" end_x=\"658076\" end_y=\"452170\" size=\"15.567859\" font=\"Microsoft YaHei\" font_color_a=\"255\" font_color_r=\"0\" font_color_g=\"0\" font_color_b=\"0\">?SCF?</RetName>\r\n<RetName start_x=\"649831\" start_y=\"431049\" end_x=\"654597\" end_y=\"429944\" size=\"17.680218\" font=\"Microsoft YaHei\" font_color_a=\"255\" font_color_r=\"0\" font_color_g=\"0\" font_color_b=\"0\">(Bending)</RetName>\r\n<RetName start_x=\"655331\" start_y=\"431090\" end_x=\"659608\" end_y=\"429920\" size=\"18.719744\" font=\"Microsoft YaHei\" font_color_a=\"255\" font_color_r=\"0\" font_color_g=\"0\" font_color_b=\"0\">(Bending)</RetName>\r\n<RetName start_x=\"621329\" start_y=\"420966\" end_x=\"627056\" end_y=\"419474\" size=\"23.872015\" font=\"Microsoft YaHei\" font_color_a=\"255\" font_color_r=\"0\" font_color_g=\"0\" font_color_b=\"0\">?3D?</RetName>\r\n<RetName start_x=\"628909\" start_y=\"420799\" end_x=\"634525\" end_y=\"419605\" size=\"23.872015\" font=\"Microsoft YaHei\" font_color_a=\"255\" font_color_r=\"0\" font_color_g=\"0\" font_color_b=\"0\">?3D?</RetName>\r\n<RetName start_x=\"645973\" start_y=\"451577\" end_x=\"648015\" end_y=\"446691\" size=\"32.671982\" font=\"Microsoft YaHei\" font_color_a=\"255\" font_color_r=\"0\" font_color_g=\"0\" font_color_b=\"0\">4 5 2</RetName>\r\n<RetName start_x=\"600479\" start_y=\"392989\" end_x=\"603741\" end_y=\"391887\" size=\"17.632551\" font=\"Microsoft YaHei\" font_color_a=\"255\" font_color_r=\"0\" font_color_g=\"0\" font_color_b=\"0\">PPF300</RetName>\r\n<RetName start_x=\"628125\" start_y=\"368303\" end_x=\"632547\" end_y=\"366548\" size=\"28.080135\" font=\"Microsoft YaHei\" font_color_a=\"255\" font_color_r=\"0\" font_color_g=\"0\" font_color_b=\"0\">LOC N</RetName>\r\n<RetName start_x=\"647080\" start_y=\"498328\" end_x=\"654242\" end_y=\"496733\" size=\"25.519627\" font=\"Microsoft YaHei\" font_color_a=\"255\" font_color_r=\"0\" font_color_g=\"0\" font_color_b=\"0\">4   0   6</RetName>\r\n<RetName start_x=\"638931\" start_y=\"498138\" end_x=\"642114\" end_y=\"496862\" size=\"25.519627\" font=\"Microsoft YaHei\" font_color_a=\"255\" font_color_r=\"0\" font_color_g=\"0\" font_color_b=\"0\">4 0 5</RetName>\r\n<RetName start_x=\"643689\" start_y=\"440344\" end_x=\"647693\" end_y=\"439068\" size=\"20.415930\" font=\"Microsoft YaHei\" font_color_a=\"255\" font_color_r=\"0\" font_color_g=\"0\" font_color_b=\"0\">4 5 1</RetName>\r\n<RetName start_x=\"655568\" start_y=\"417855\" end_x=\"661226\" end_y=\"411627\" size=\"31.856062\" font=\"Microsoft YaHei\" font_color_a=\"255\" font_color_r=\"0\" font_color_g=\"0\" font_color_b=\"0\">ic tape#M</RetName>\r\n<RetName start_x=\"647795\" start_y=\"427426\" end_x=\"649532\" end_y=\"424030\" size=\"27.792120\" font=\"Microsoft YaHei\" font_color_a=\"255\" font_color_r=\"0\" font_color_g=\"0\" font_color_b=\"0\">4 1 1</RetName>\r\n<RetName start_x=\"647608\" start_y=\"417856\" end_x=\"649551\" end_y=\"413976\" size=\"31.087822\" font=\"Microsoft YaHei\" font_color_a=\"255\" font_color_r=\"0\" font_color_g=\"0\" font_color_b=\"0\">4  1 2</RetName>\r\n<RetName start_x=\"647700\" start_y=\"408560\" end_x=\"649529\" end_y=\"403822\" size=\"29.263393\" font=\"Microsoft YaHei\" font_color_a=\"255\" font_color_r=\"0\" font_color_g=\"0\" font_color_b=\"0\">4 1 3</RetName>\r\n<RetName start_x=\"650069\" start_y=\"418062\" end_x=\"655142\" end_y=\"411122\" size=\"35.279686\" font=\"Microsoft YaHei\" font_color_a=\"255\" font_color_r=\"0\" font_color_g=\"0\" font_color_b=\"0\">ic tape#N</RetName>\r\n<RetName start_x=\"647703\" start_y=\"398000\" end_x=\"649812\" end_y=\"394355\" size=\"33.744236\" font=\"Microsoft YaHei\" font_color_a=\"255\" font_color_r=\"0\" font_color_g=\"0\" font_color_b=\"0\">4 1 4</RetName>\r\n<RetName start_x=\"647727\" start_y=\"390609\" end_x=\"650204\" end_y=\"380979\" size=\"39.631832\" font=\"Microsoft YaHei\" font_color_a=\"255\" font_color_r=\"0\" font_color_g=\"0\" font_color_b=\"0\">4 1 5</RetName>\r\n<RetName start_x=\"623103\" start_y=\"355686\" end_x=\"628398\" end_y=\"353223\" size=\"39.407578\" font=\"Microsoft YaHei\" font_color_a=\"255\" font_color_r=\"0\" font_color_g=\"0\" font_color_b=\"0\">4 1 9</RetName>\r\n<RetName start_x=\"636550\" start_y=\"355419\" end_x=\"642218\" end_y=\"352746\" size=\"42.767578\" font=\"Microsoft YaHei\" font_color_a=\"255\" font_color_r=\"0\" font_color_g=\"0\" font_color_b=\"0\">4 1 8</RetName>\r\n<RetName start_x=\"646668\" start_y=\"354906\" end_x=\"652008\" end_y=\"353048\" size=\"29.728081\" font=\"Microsoft YaHei\" font_color_a=\"255\" font_color_r=\"0\" font_color_g=\"0\" font_color_b=\"0\">4 1 7</RetName>\r\n<RetName start_x=\"644841\" start_y=\"472065\" end_x=\"646889\" end_y=\"468026\" size=\"32.767544\" font=\"Microsoft YaHei\" font_color_a=\"255\" font_color_r=\"0\" font_color_g=\"0\" font_color_b=\"0\">4 0 8</RetName>\r\n<RetName start_x=\"608387\" start_y=\"410981\" end_x=\"610467\" end_y=\"404255\" size=\"33.280151\" font=\"Microsoft YaHei\" font_color_a=\"255\" font_color_r=\"0\" font_color_g=\"0\" font_color_b=\"0\">4 5 4</RetName>\r\n<RetName start_x=\"608273\" start_y=\"422720\" end_x=\"610752\" end_y=\"416013\" size=\"39.663979\" font=\"Microsoft YaHei\" font_color_a=\"255\" font_color_r=\"0\" font_color_g=\"0\" font_color_b=\"0\">4 5 3</RetName>\r\n<RetName start_x=\"621723\" start_y=\"498211\" end_x=\"625750\" end_y=\"496714\" size=\"29.936092\" font=\"Microsoft YaHei\" font_color_a=\"255\" font_color_r=\"0\" font_color_g=\"0\" font_color_b=\"0\">404</RetName>\r\n<RetName start_x=\"629215\" start_y=\"498291\" end_x=\"633243\" end_y=\"496794\" size=\"29.936092\" font=\"Microsoft YaHei\" font_color_a=\"255\" font_color_r=\"0\" font_color_g=\"0\" font_color_b=\"0\">455</RetName>\r\n<RetName start_x=\"609783\" start_y=\"362637\" end_x=\"613302\" end_y=\"361140\" size=\"29.936092\" font=\"Microsoft YaHei\" font_color_a=\"255\" font_color_r=\"0\" font_color_g=\"0\" font_color_b=\"0\">456</RetName>\r\n<RetName start_x=\"635686\" start_y=\"509108\" end_x=\"639015\" end_y=\"507611\" size=\"29.936092\" font=\"Microsoft YaHei\" font_color_a=\"255\" font_color_r=\"0\" font_color_g=\"0\" font_color_b=\"0\">402</RetName>\r\n<RetName start_x=\"646072\" start_y=\"509107\" end_x=\"649401\" end_y=\"507611\" size=\"29.936092\" font=\"Microsoft YaHei\" font_color_a=\"255\" font_color_r=\"0\" font_color_g=\"0\" font_color_b=\"0\">401</RetName>\r\n<RetName start_x=\"680233\" start_y=\"508796\" end_x=\"686580\" end_y=\"507299\" size=\"29.936092\" font=\"Microsoft YaHei\" font_color_a=\"255\" font_color_r=\"0\" font_color_g=\"0\" font_color_b=\"0\">457</RetName>\r\n<RetName start_x=\"670448\" start_y=\"509018\" end_x=\"674299\" end_y=\"507140\" size=\"30.047871\" font=\"Microsoft YaHei\" font_color_a=\"255\" font_color_r=\"0\" font_color_g=\"0\" font_color_b=\"0\">407</RetName>\r\n<RetName start_x=\"622154\" start_y=\"366060\" end_x=\"627639\" end_y=\"364496\" size=\"25.023912\" font=\"Microsoft YaHei\" font_color_a=\"255\" font_color_r=\"0\" font_color_g=\"0\" font_color_b=\"0\">O-cut)</RetName>\r\n<RetName start_x=\"627821\" start_y=\"365818\" end_x=\"632464\" end_y=\"364386\" size=\"22.912251\" font=\"Microsoft YaHei\" font_color_a=\"255\" font_color_r=\"0\" font_color_g=\"0\" font_color_b=\"0\">O-cut)</RetName>\r\n<RetName start_x=\"611124\" start_y=\"372300\" end_x=\"613110\" end_y=\"371622\" size=\"10.847971\" font=\"Microsoft YaHei\" font_color_a=\"255\" font_color_r=\"0\" font_color_g=\"0\" font_color_b=\"0\">(ODD)</RetName>\r\n<RetName start_x=\"654150\" start_y=\"500890\" end_x=\"656423\" end_y=\"500090\" size=\"16.000000\" font=\"Microsoft YaHei\" font_color_a=\"255\" font_color_r=\"0\" font_color_g=\"0\" font_color_b=\"0\"></RetName>\r\n</MapRetCfg>\r\n","type":"1"}]}